{
    "id": "typography",
    "name": "Typography",
    "hasScript": "yes",
    "items" : {
        "fonts": [
            {
                "heading": "1",
                "fontName" : "Gordita Normal",
                "fontSize": "36px",
                "className": "font-gordita",
                "title": "Heading H1"
            },

            {
                "heading": "2",
                "fontName" : "Gordita Normal",
                "fontSize": "32px",
                "className": "font-gordita",
                "title": "Heading H2"
            },

            {
                "heading": "3",
                "fontName" : "Gordita Normal",
                "fontSize": "28px",
                "className": "font-gordita",
                "title": "Heading H3"
            },

            {
                "heading": "4",
                "fontName" : "Gordita Normal",
                "fontSize": "24px",
                "className": "font-gordita",
                "title": "Heading H4"
            },


            {
                "heading": "5",
                "fontName" : "Gordita Normal",
                "fontSize": "20px",
                "className": "font-gordita",
                "title": "Heading H5"
            },

            {
                "heading": "6",
                "fontName" : "Gordita Normal",
                "fontSize": "16px",
                "className": "font-gordita",
                "title": "Heading H6"
            }


        ],
        "paragraphsName": "Paragraphs",
        "paragraphs": [
            {
                "className": "",
                "text": "SEO is a marketing tactic that costs five percent of overall budget but brings in more than 20 percent of revenue for many Fortune 500 companies, and yet very few of them prioritize it. Instead, while slowly changing, too many CMOS still favor paid search, which costs 20 percent and brings in… 20 percent. In search, businesses need to shift priorities. Now."
            },
            {
                "className": "",
                "text": "Link volume is one of the most powerful signals search engines use to rank websites. There’s a way to use links to generate better search results, but too many marketers rely on traditional (or even black hat) tactics that just don’t work anymore."
            },
            {
                "className": "",
                "text": "Huge to be recognized at the 2014 “Made in NY” Awards for the company’s contribution to New York’s creative economy."
            }
        ]
    }
}